pandas_upsert_to_mysql/__init__.py
pandas_upsert_to_mysql/core.py
pandas_upsert_to_mysql/table.py
pandas_upsert_to_mysql-0.0.3.dist-info/LICENSE
pandas_upsert_to_mysql-0.0.3.dist-info/METADATA
pandas_upsert_to_mysql-0.0.3.dist-info/WHEEL
pandas_upsert_to_mysql-0.0.3.dist-info/top_level.txt
pandas_upsert_to_mysql-0.0.3.dist-info/RECORD
