Metadata-Version: 2.1
Name: pandas-upsert-to-mysql
Version: 0.0.3
Summary: Enhanced `to_sql` method in pandas DataFrame, for MySQL database only.
Home-page: https://github.com/LawrentChen/pandas_upsert_to_mysql
Author: LawrentChen
Author-email: laurant.chen@gmail.com
License: UNKNOWN
Platform: UNKNOWN
Classifier: Programming Language :: Python :: 3
Classifier: License :: OSI Approved :: MIT License
Classifier: Operating System :: OS Independent
Requires-Python: >=3.6
Requires-Dist: pandas
Requires-Dist: SQLAlchemy
Requires-Dist: mysqlclient
